geoshoplib/__init__.py
geoshoplib/lib/__init__.py
geoshoplib/lib/soap/services.py
geoshoplib/lib/soap/__init__.py
geoshoplib-0.4.0.dist-info/DESCRIPTION.rst
geoshoplib-0.4.0.dist-info/WHEEL
geoshoplib-0.4.0.dist-info/metadata.json
geoshoplib-0.4.0.dist-info/METADATA
geoshoplib-0.4.0.dist-info/RECORD
geoshoplib-0.4.0.dist-info/top_level.txt
