Metadata-Version: 2.0
Name: geoshoplib
Version: 0.4.0
Summary: Python API to access geoshop services.
Home-page: https://gitlab.com/gf-bl/geoshoplib
Author: Clemens Rudert
Author-email: clemens.rudert@bl.ch
License: GNU General Public License
Keywords: api geoshop infogrips soap xml
Platform: UNKNOWN
Classifier: Development Status :: 3 - Alpha
Classifier: Intended Audience :: Developers
Classifier: Programming Language :: Python
Classifier: Topic :: Internet :: WWW/HTTP
Requires-Dist: httplib2
Requires-Dist: untangle
